llama_index/readers/earnings_call_transcript/__init__.py
llama_index/readers/earnings_call_transcript/base.py
llama_index/readers/earnings_call_transcript/utils.py
llama_index_readers_earnings_call_transcript-0.4.1.dist-info/METADATA
llama_index_readers_earnings_call_transcript-0.4.1.dist-info/WHEEL
llama_index_readers_earnings_call_transcript-0.4.1.dist-info/licenses/LICENSE
llama_index_readers_earnings_call_transcript-0.4.1.dist-info/RECORD
