Metadata-Version: 2.4
Name: llama-index-readers-earnings-call-transcript
Version: 0.4.1
Summary: llama-index readers earnings_call_transcript integration
Author-email: Your Name <you@example.com>
Maintainer: Athe-kunal
License-Expression: MIT
License-File: LICENSE
Keywords: Earning calls,Finance,Investor
Requires-Python: <4.0,>=3.9
Requires-Dist: llama-index-core<0.15,>=0.13.0
Requires-Dist: requests<3,>=2.31.0
Requires-Dist: tenacity<9,>=8.2.3
